pyinite/__init__.py
pyinite/Dll/win32dll.exe
pyinite-0.1.9.dist-info/METADATA
pyinite-0.1.9.dist-info/WHEEL
pyinite-0.1.9.dist-info/top_level.txt
pyinite-0.1.9.dist-info/RECORD
