Metadata-Version: 2.4
Name: pyinite
Version: 0.1.9
Summary: A Python lib you can use to initialize your Python scripts (Console based / Windowed)
Author: Guillaume Plagier
Dynamic: author
Dynamic: summary
